Metadata-Version: 2.1
Name: bas-remote-python-v2
Version: 2.0.2
Summary: Python library, which allows you to automate Google Chrome browser via BAS software.
Home-page: https://github.com/sergerdn/bas-remote-python-v2
License: MIT
Keywords: visual-programming-language,browserautomationstudio,bas-remote-control,bas-remote-client,bot-framework,bas-remote,bas-client,automation,chromium,imacros,windows,desktop,browser,grabber,poster,macros,bas,ide,cef,bot
Author: Sergerdn
Requires-Python: >=3.7,<4.0
Classifier: Intended Audience :: Developers
Classifier: License :: OSI Approved :: MIT License
Classifier: Programming Language :: Python :: 3
Classifier: Programming Language :: Python :: 3.7
Classifier: Programming Language :: Python :: 3.8
Classifier: Programming Language :: Python :: 3.9
Classifier: Programming Language :: Python :: 3.10
Classifier: Programming Language :: Python :: 3
Classifier: Programming Language :: Python :: 3.10
Classifier: Programming Language :: Python :: 3.7
Classifier: Programming Language :: Python :: 3.8
Classifier: Programming Language :: Python :: 3.9
Requires-Dist: aiofiles (>=22.1.0,<23.0.0)
Requires-Dist: aiohttp (>=3.8.1,<4.0.0)
Requires-Dist: dataclasses-json (>=0.5.7,<0.6.0)
Requires-Dist: filelock (>=3.8.0,<4.0.0)
Requires-Dist: pyee (>=9.0.4,<10.0.0)
Requires-Dist: websockets (>=10.3,<11.0)
Project-URL: Bug Tracker, https://github.com/sergerdn/bas-remote-python-v2/issues
Project-URL: Documentation, https://github.com/CheshireCaat/bas-remote-python/wiki
Project-URL: Repository, https://github.com/sergerdn/bas-remote-python-v2
